SolixBLE.py
solixble-2.1.1.dist-info/licenses/LICENSE.txt
solixble-2.1.1.dist-info/METADATA
solixble-2.1.1.dist-info/WHEEL
solixble-2.1.1.dist-info/top_level.txt
solixble-2.1.1.dist-info/RECORD
