Metadata-Version: 2.4
Name: SolixBLE
Version: 2.1.1
Summary: Python module for monitoring Bluetooth Anker Solix devices
Author-email: Harvey Lelliott <harveylelliott@duck.com>
License: MIT License
Project-URL: Homepage, https://github.com/flip-dots/SolixBLE
Project-URL: Repository, https://github.com/flip-dots/SolixBLE
Project-URL: Issues, https://github.com/flip-dots/SolixBLE/issues
Keywords: Anker,Solix,BLE,Home Assistant
Classifier: Development Status :: 3 - Alpha
Classifier: Intended Audience :: Developers
Classifier: Topic :: Home Automation
Classifier: License :: OSI Approved :: MIT License
Classifier: Framework :: AsyncIO
Classifier: Operating System :: Microsoft :: Windows :: Windows 10
Classifier: Operating System :: POSIX :: Linux
Classifier: Operating System :: MacOS :: MacOS X
Classifier: Programming Language :: Python :: 3.11
Requires-Python: >=3.11
License-File: LICENSE.txt
Requires-Dist: bleak>=0.19.0
Requires-Dist: bleak-retry-connector
Dynamic: license-file
